reqstool/__init__.py
reqstool/command.py
reqstool/commands/exit_codes.py
reqstool/commands/generate_json/generate_json.py
reqstool/commands/report/report.py
reqstool/commands/report/criterias/group_by.py
reqstool/commands/report/criterias/sort_by.py
reqstool/commands/report/templates/annotation_impls.j2
reqstool/commands/report/templates/annotation_tests.j2
reqstool/commands/report/templates/mvrs.j2
reqstool/commands/report/templates/report.j2
reqstool/commands/report/templates/req_references.j2
reqstool/commands/report/templates/requirements.j2
reqstool/commands/report/templates/svcs.j2
reqstool/commands/report/templates/total_statistics.j2
reqstool/commands/status/statistics_container.py
reqstool/commands/status/statistics_generator.py
reqstool/commands/status/status.py
reqstool/common/jinja2.py
reqstool/common/utils.py
reqstool/common/validator_error_holder.py
reqstool/common/dataclasses/lifecycle.py
reqstool/common/dataclasses/urn_id.py
reqstool/common/validators/lifecycle_validator.py
reqstool/common/validators/semantic_validator.py
reqstool/common/validators/syntax_validator.py
reqstool/expression_languages/generic_el.py
reqstool/expression_languages/requirements_el.py
reqstool/expression_languages/svcs_el.py
reqstool/filters/id_filters.py
reqstool/filters/requirements_filters.py
reqstool/filters/svcs_filters.py
reqstool/location_resolver/location_resolver.py
reqstool/locations/git_location.py
reqstool/locations/local_location.py
reqstool/locations/location.py
reqstool/locations/maven_location.py
reqstool/locations/pypi_location.py
reqstool/model_generators/annotations_model_generator.py
reqstool/model_generators/combined_indexed_dataset_generator.py
reqstool/model_generators/combined_raw_datasets_generator.py
reqstool/model_generators/mvrs_model_generator.py
reqstool/model_generators/requirements_model_generator.py
reqstool/model_generators/svcs_model_generator.py
reqstool/model_generators/testdata_model_generator.py
reqstool/models/annotations.py
reqstool-0.5.11.dist-info/METADATA
reqstool-0.5.11.dist-info/WHEEL
reqstool-0.5.11.dist-info/entry_points.txt
reqstool-0.5.11.dist-info/licenses/LICENSE
reqstool-0.5.11.dist-info/RECORD
