Metadata-Version: 2.4
Name: reqstool
Version: 0.5.11
Summary: A tool for managing requirements with related tests and test results.
Project-URL: Source, https://github.com/Luftfartsverket/reqstool-client
Author-email: LFV <info@lfv.se>
License-File: LICENSE
Classifier: Development Status :: 3 - Alpha
Classifier: Operating System :: OS Independent
Classifier: Programming Language :: Python :: 3
Requires-Python: >=3.10
Requires-Dist: beautifulsoup4==4.13.3
Requires-Dist: colorama==0.4.6
Requires-Dist: distlib==0.3.9
Requires-Dist: jinja2==3.1.6
Requires-Dist: jsonpickle==4.0.5
Requires-Dist: jsonschema[format-nongpl]==4.23.0
Requires-Dist: lark==1.2.2
Requires-Dist: maven-artifact==0.3.4
Requires-Dist: packaging==24.2
Requires-Dist: pygit2==1.17.0
Requires-Dist: referencing==0.36.2
Requires-Dist: reqstool-python-decorators==0.0.7
Requires-Dist: requests-file==2.1.0
Requires-Dist: requests==2.32.3
Requires-Dist: ruamel-yaml==0.18.10
Requires-Dist: tabulate==0.9.0
Requires-Dist: xmldict==0.4.1
